srim/__init__.py
srim/config.py
srim/input.py
srim/output.py
srim/plot.py
srim/srim.py
srim/core/__init__.py
srim/core/element.py
srim/core/elementdb.py
srim/core/ion.py
srim/core/layer.py
srim/core/material.py
srim/core/target.py
srim/core/units.py
srim/core/utils.py
srim/data/elements.yaml
pysrim-0.5.10.dist-info/LICENSE
pysrim-0.5.10.dist-info/METADATA
pysrim-0.5.10.dist-info/WHEEL
pysrim-0.5.10.dist-info/top_level.txt
pysrim-0.5.10.dist-info/RECORD
