Metadata-Version: 2.1
Name: pysrim
Version: 0.5.10
Summary: Srim Automation of Tasks via Python
Home-page: https://gitlab.com/costrouc/pysrim
Author: Christopher Ostrouchov
Author-email: chris.ostrouchov+pysrim@gmail.com
License: MIT
Download-URL: https://gitlab.com/costrouc/pysrim/repository/master/archive.zip
Keywords: material srim automation plotting
Platform: UNKNOWN
Classifier: Development Status :: 4 - Beta
Classifier: Natural Language :: English
Classifier: License :: OSI Approved :: MIT License
Classifier: Programming Language :: Python :: 2.6
Classifier: Programming Language :: Python :: 2.7
Classifier: Programming Language :: Python :: 3.3
Classifier: Programming Language :: Python :: 3.4
Classifier: Programming Language :: Python :: 3.5
Classifier: Programming Language :: Python :: 3.6
Classifier: Programming Language :: Python :: 3.7
Requires-Dist: pyyaml
Requires-Dist: numpy (>=1.10.0)
